Metadata-Version: 2.1
Name: flask-restful-api
Version: 1.0
Summary: Make restful api simple and fast
Author-email: glebisi@yandex.ru
